cubicweb_folder/__init__.py
cubicweb_folder/__pkginfo__.py
cubicweb_folder/entities.py
cubicweb_folder/hooks.py
cubicweb_folder/schema.py
cubicweb_folder/uiprops.py
cubicweb_folder/views.py
cubicweb_folder/data/icon_folder.gif
cubicweb_folder/i18n/en.po
cubicweb_folder/i18n/fr.po
cubicweb_folder/migration/1.0.1_Any.py
cubicweb_folder/migration/1.5.0_Any.py
cubicweb_folder/migration/postcreate.py
cubicweb_folder/wdoc/add_folder_fr.rst
cubicweb_folder/wdoc/toc.xml
cubicweb_folder-3.1.0.dist-info/METADATA
cubicweb_folder-3.1.0.dist-info/WHEEL
cubicweb_folder-3.1.0.dist-info/entry_points.txt
cubicweb_folder-3.1.0.dist-info/top_level.txt
cubicweb_folder-3.1.0.dist-info/RECORD
